[{"model": "admin.logentry", "pk": 1, "fields": {"action_time": "2023-02-08T18:16:05.735Z", "user": 1, "content_type": 4, "object_id": "1", "object_repr": "maula", "action_flag": 2, "change_message": "[{\"changed\": {\"fields\": [\"First name\", \"Last name\"]}}]"}}, {"model": "admin.logentry", "pk": 2, "fields": {"action_time": "2023-02-13T07:27:03.296Z", "user": 1, "content_type": 7, "object_id": "1", "object_repr": "1. Akame ga Kill !", "action_flag": 1, "change_message": "[{\"added\": {}}]"}}, {"model": "admin.logentry", "pk": 3, "fields": {"action_time": "2023-02-13T07:28:37.407Z", "user": 1, "content_type": 7, "object_id": "2", "object_repr": "2. Aki-Sora", "action_flag": 1, "change_message": "[{\"added\": {}}]"}}, {"model": "admin.logentry", "pk": 4, "fields": {"action_time": "2023-02-13T07:29:42.437Z", "user": 1, "content_type": 7, "object_id": "3", "object_repr": "3. Aki-Sora - Yume no Naka", "action_flag": 1, "change_message": "[{\"added\": {}}]"}}, {"model": "admin.logentry", "pk": 5, "fields": {"action_time": "2023-02-13T07:31:24.513Z", "user": 1, "content_type": 7, "object_id": "4", "object_repr": "4. Blood C", "action_flag": 1, "change_message": "[{\"added\": {}}]"}}, {"model": "admin.logentry", "pk": 6, "fields": {"action_time": "2023-02-13T07:32:46.495Z", "user": 1, "content_type": 7, "object_id": "5", "object_repr": "5. Blood C - The Last Dark", "action_flag": 1, "change_message": "[{\"added\": {}}]"}}, {"model": "admin.logentry", "pk": 7, "fields": {"action_time": "2023-02-13T08:52:07.697Z", "user": 1, "content_type": 7, "object_id": "6", "object_repr": "6. Dummy Test Insert Then Delete it", "action_flag": 1, "change_message": "[{\"added\": {}}]"}}, {"model": "admin.logentry", "pk": 8, "fields": {"action_time": "2023-02-13T08:55:10.809Z", "user": 1, "content_type": 7, "object_id": "7", "object_repr": "7. Dummy Test Insert Then Delete it", "action_flag": 1, "change_message": "[{\"added\": {}}]"}}, {"model": "admin.logentry", "pk": 9, "fields": {"action_time": "2023-02-13T12:46:10.168Z", "user": 1, "content_type": 7, "object_id": "10", "object_repr": "10. Itai no wa Iya nano de Bougyoryoku ni Kyokufuri Shitai to Omoimasu", "action_flag": 1, "change_message": "[{\"added\": {}}]"}}, {"model": "admin.logentry", "pk": 10, "fields": {"action_time": "2023-02-13T12:47:24.353Z", "user": 1, "content_type": 7, "object_id": "11", "object_repr": "11. Code Geass R1 - Hangyaku no Lelouch", "action_flag": 1, "change_message": "[{\"added\": {}}]"}}, {"model": "admin.logentry", "pk": 11, "fields": {"action_time": "2023-02-13T12:48:13.827Z", "user": 1, "content_type": 7, "object_id": "12", "object_repr": "12. Code Geass R2 - Hangyaku no Lelouch", "action_flag": 1, "change_message": "[{\"added\": {}}]"}}, {"model": "admin.logentry", "pk": 12, "fields": {"action_time": "2023-02-13T12:49:32.299Z", "user": 1, "content_type": 7, "object_id": "13", "object_repr": "13. Code Geass Boukoku no Akito 1 (Yokuryuu wa Maiorita)", "action_flag": 1, "change_message": "[{\"added\": {}}]"}}, {"model": "admin.logentry", "pk": 13, "fields": {"action_time": "2023-02-13T12:50:18.292Z", "user": 1, "content_type": 7, "object_id": "14", "object_repr": "14. Code Geass Boukoku no Akito 2 (Hikisakareshi Yokuryuu)", "action_flag": 1, "change_message": "[{\"added\": {}}]"}}, {"model": "admin.logentry", "pk": 14, "fields": {"action_time": "2023-02-13T12:51:01.763Z", "user": 1, "content_type": 7, "object_id": "15", "object_repr": "15. Code Geass Boukoku no Akito 3 (Kagayaku Mono Ten yori Otsu)", "action_flag": 1, "change_message": "[{\"added\": {}}]"}}, {"model": "admin.logentry", "pk": 15, "fields": {"action_time": "2023-02-13T12:51:58.462Z", "user": 1, "content_type": 7, "object_id": "16", "object_repr": "16. Code Geass Boukoku no Akito 4 (Nikushimi no Kioku kara)", "action_flag": 1, "change_message": "[{\"added\": {}}]"}}, {"model": "admin.logentry", "pk": 16, "fields": {"action_time": "2023-02-13T12:52:39.071Z", "user": 1, "content_type": 7, "object_id": "17", "object_repr": "17. Code Geass Boukoku no Akito 5 (Itoshiki Mono-tachi e)", "action_flag": 1, "change_message": "[{\"added\": {}}]"}}, {"model": "admin.logentry", "pk": 17, "fields": {"action_time": "2023-02-13T12:53:23.259Z", "user": 1, "content_type": 7, "object_id": "18", "object_repr": "18. Code Geass Fukkatsu no Lelouch", "action_flag": 1, "change_message": "[{\"added\": {}}]"}}, {"model": "admin.logentry", "pk": 18, "fields": {"action_time": "2023-02-13T12:54:03.220Z", "user": 1, "content_type": 7, "object_id": "19", "object_repr": "19. Corpse Party - Bougyakusareta Tamashii no Jukyou", "action_flag": 1, "change_message": "[{\"added\": {}}]"}}, {"model": "admin.logentry", "pk": 19, "fields": {"action_time": "2023-02-13T12:55:12.780Z", "user": 1, "content_type": 7, "object_id": "20", "object_repr": "20. Corpse Party - Missing Footage", "action_flag": 1, "change_message": "[{\"added\": {}}]"}}, {"model": "admin.logentry", "pk": 20, "fields": {"action_time": "2023-02-13T12:55:58.492Z", "user": 1, "content_type": 7, "object_id": "21", "object_repr": "21. Dakara Boku wa, H ga Dekinai", "action_flag": 1, "change_message": "[{\"added\": {}}]"}}, {"model": "admin.logentry", "pk": 21, "fields": {"action_time": "2023-02-13T12:56:44.464Z", "user": 1, "content_type": 7, "object_id": "22", "object_repr": "22. Darling in the FranXX", "action_flag": 1, "change_message": "[{\"added\": {}}]"}}, {"model": "admin.logentry", "pk": 22, "fields": {"action_time": "2023-02-13T12:57:25.266Z", "user": 1, "content_type": 7, "object_id": "23", "object_repr": "23. Date A Live 1", "action_flag": 1, "change_message": "[{\"added\": {}}]"}}, {"model": "admin.logentry", "pk": 23, "fields": {"action_time": "2023-02-13T12:58:01.607Z", "user": 1, "content_type": 7, "object_id": "24", "object_repr": "24. Date A Live 2", "action_flag": 1, "change_message": "[{\"added\": {}}]"}}, {"model": "admin.logentry", "pk": 24, "fields": {"action_time": "2023-02-13T12:58:38.646Z", "user": 1, "content_type": 7, "object_id": "25", "object_repr": "25. Date A Live 3", "action_flag": 1, "change_message": "[{\"added\": {}}]"}}, {"model": "admin.logentry", "pk": 25, "fields": {"action_time": "2023-02-13T13:00:52.333Z", "user": 1, "content_type": 7, "object_id": "26", "object_repr": "26. Date A Live 4", "action_flag": 1, "change_message": "[{\"added\": {}}]"}}, {"model": "admin.logentry", "pk": 26, "fields": {"action_time": "2023-02-13T13:01:35.338Z", "user": 1, "content_type": 7, "object_id": "27", "object_repr": "27. Date A Live Movie: Mayuri Judgement", "action_flag": 1, "change_message": "[{\"added\": {}}]"}}, {"model": "admin.logentry", "pk": 27, "fields": {"action_time": "2023-02-13T13:02:36.928Z", "user": 1, "content_type": 7, "object_id": "28", "object_repr": "28. Date A Bullet 1 - Dead or Bullet's", "action_flag": 1, "change_message": "[{\"added\": {}}]"}}, {"model": "admin.logentry", "pk": 28, "fields": {"action_time": "2023-02-13T13:03:25.275Z", "user": 1, "content_type": 7, "object_id": "29", "object_repr": "29. Date A Bullet 2 - Queen's or Nightmare", "action_flag": 1, "change_message": "[{\"added\": {}}]"}}, {"model": "admin.logentry", "pk": 29, "fields": {"action_time": "2023-02-13T13:04:33.491Z", "user": 1, "content_type": 7, "object_id": "30", "object_repr": "30. Elfen Lied", "action_flag": 1, "change_message": "[{\"added\": {}}]"}}, {"model": "admin.logentry", "pk": 30, "fields": {"action_time": "2023-02-13T13:05:19.881Z", "user": 1, "content_type": 7, "object_id": "31", "object_repr": "31. Neon Genesis Evangelion", "action_flag": 1, "change_message": "[{\"added\": {}}]"}}, {"model": "admin.logentry", "pk": 31, "fields": {"action_time": "2023-02-13T13:05:59.889Z", "user": 1, "content_type": 7, "object_id": "32", "object_repr": "32. Neon Genesis Evangelion: The End of Evangelion", "action_flag": 1, "change_message": "[{\"added\": {}}]"}}, {"model": "admin.logentry", "pk": 32, "fields": {"action_time": "2023-02-15T08:43:04.235Z", "user": 1, "content_type": 9, "object_id": "1", "object_repr": "Inisialisasi Konten Pertama", "action_flag": 1, "change_message": "[{\"added\": {}}]"}}, {"model": "admin.logentry", "pk": 33, "fields": {"action_time": "2023-02-15T08:43:24.533Z", "user": 1, "content_type": 9, "object_id": "1", "object_repr": "Inisialisasi Konten Pertama", "action_flag": 2, "change_message": "[]"}}, {"model": "admin.logentry", "pk": 34, "fields": {"action_time": "2023-02-15T08:44:44.732Z", "user": 1, "content_type": 9, "object_id": "2", "object_repr": "Inisialisasi Konten Kedua", "action_flag": 1, "change_message": "[{\"added\": {}}]"}}, {"model": "admin.logentry", "pk": 35, "fields": {"action_time": "2023-02-15T09:11:03.699Z", "user": 1, "content_type": 9, "object_id": "3", "object_repr": "PENGUMUMAN MAINTENANCE", "action_flag": 1, "change_message": "[{\"added\": {}}]"}}, {"model": "admin.logentry", "pk": 36, "fields": {"action_time": "2023-02-15T09:11:53.818Z", "user": 1, "content_type": 9, "object_id": "4", "object_repr": "Serial BORUTO Dikabarkan Hiatus, Masashi Fokus Remake", "action_flag": 1, "change_message": "[{\"added\": {}}]"}}, {"model": "admin.logentry", "pk": 37, "fields": {"action_time": "2023-02-15T11:45:05.051Z", "user": 1, "content_type": 9, "object_id": "5", "object_repr": "My Hero Academia Season 5 Siap Ditayangkan NET", "action_flag": 1, "change_message": "[{\"added\": {}}]"}}, {"model": "auth.permission", "pk": 1, "fields": {"name": "Can add log entry", "content_type": 1, "codename": "add_logentry"}}, {"model": "auth.permission", "pk": 2, "fields": {"name": "Can change log entry", "content_type": 1, "codename": "change_logentry"}}, {"model": "auth.permission", "pk": 3, "fields": {"name": "Can delete log entry", "content_type": 1, "codename": "delete_logentry"}}, {"model": "auth.permission", "pk": 4, "fields": {"name": "Can view log entry", "content_type": 1, "codename": "view_logentry"}}, {"model": "auth.permission", "pk": 5, "fields": {"name": "Can add permission", "content_type": 2, "codename": "add_permission"}}, {"model": "auth.permission", "pk": 6, "fields": {"name": "Can change permission", "content_type": 2, "codename": "change_permission"}}, {"model": "auth.permission", "pk": 7, "fields": {"name": "Can delete permission", "content_type": 2, "codename": "delete_permission"}}, {"model": "auth.permission", "pk": 8, "fields": {"name": "Can view permission", "content_type": 2, "codename": "view_permission"}}, {"model": "auth.permission", "pk": 9, "fields": {"name": "Can add group", "content_type": 3, "codename": "add_group"}}, {"model": "auth.permission", "pk": 10, "fields": {"name": "Can change group", "content_type": 3, "codename": "change_group"}}, {"model": "auth.permission", "pk": 11, "fields": {"name": "Can delete group", "content_type": 3, "codename": "delete_group"}}, {"model": "auth.permission", "pk": 12, "fields": {"name": "Can view group", "content_type": 3, "codename": "view_group"}}, {"model": "auth.permission", "pk": 13, "fields": {"name": "Can add user", "content_type": 4, "codename": "add_user"}}, {"model": "auth.permission", "pk": 14, "fields": {"name": "Can change user", "content_type": 4, "codename": "change_user"}}, {"model": "auth.permission", "pk": 15, "fields": {"name": "Can delete user", "content_type": 4, "codename": "delete_user"}}, {"model": "auth.permission", "pk": 16, "fields": {"name": "Can view user", "content_type": 4, "codename": "view_user"}}, {"model": "auth.permission", "pk": 17, "fields": {"name": "Can add content type", "content_type": 5, "codename": "add_contenttype"}}, {"model": "auth.permission", "pk": 18, "fields": {"name": "Can change content type", "content_type": 5, "codename": "change_contenttype"}}, {"model": "auth.permission", "pk": 19, "fields": {"name": "Can delete content type", "content_type": 5, "codename": "delete_contenttype"}}, {"model": "auth.permission", "pk": 20, "fields": {"name": "Can view content type", "content_type": 5, "codename": "view_contenttype"}}, {"model": "auth.permission", "pk": 21, "fields": {"name": "Can add session", "content_type": 6, "codename": "add_session"}}, {"model": "auth.permission", "pk": 22, "fields": {"name": "Can change session", "content_type": 6, "codename": "change_session"}}, {"model": "auth.permission", "pk": 23, "fields": {"name": "Can delete session", "content_type": 6, "codename": "delete_session"}}, {"model": "auth.permission", "pk": 24, "fields": {"name": "Can view session", "content_type": 6, "codename": "view_session"}}, {"model": "auth.permission", "pk": 25, "fields": {"name": "Can add anime", "content_type": 7, "codename": "add_anime"}}, {"model": "auth.permission", "pk": 26, "fields": {"name": "Can change anime", "content_type": 7, "codename": "change_anime"}}, {"model": "auth.permission", "pk": 27, "fields": {"name": "Can delete anime", "content_type": 7, "codename": "delete_anime"}}, {"model": "auth.permission", "pk": 28, "fields": {"name": "Can view anime", "content_type": 7, "codename": "view_anime"}}, {"model": "auth.permission", "pk": 29, "fields": {"name": "Can add news", "content_type": 8, "codename": "add_news"}}, {"model": "auth.permission", "pk": 30, "fields": {"name": "Can change news", "content_type": 8, "codename": "change_news"}}, {"model": "auth.permission", "pk": 31, "fields": {"name": "Can delete news", "content_type": 8, "codename": "delete_news"}}, {"model": "auth.permission", "pk": 32, "fields": {"name": "Can view news", "content_type": 8, "codename": "view_news"}}, {"model": "auth.permission", "pk": 33, "fields": {"name": "Can add berita", "content_type": 9, "codename": "add_berita"}}, {"model": "auth.permission", "pk": 34, "fields": {"name": "Can change berita", "content_type": 9, "codename": "change_berita"}}, {"model": "auth.permission", "pk": 35, "fields": {"name": "Can delete berita", "content_type": 9, "codename": "delete_berita"}}, {"model": "auth.permission", "pk": 36, "fields": {"name": "Can view berita", "content_type": 9, "codename": "view_berita"}}, {"model": "auth.user", "pk": 1, "fields": {"password": "pbkdf2_sha256$260000$YYp30Q2jOHAVe5qklmqiak$iFs7NqSUx+bTQYUPIQYQvALL9FQPB35z85PV9uIK/1Q=", "last_login": "2023-02-08T18:15:16Z", "is_superuser": true, "username": "maula", "first_name": "Maulana Aji", "last_name": "Wicaksono", "email": "maulanawesome5@gmail.com", "is_staff": true, "is_active": true, "date_joined": "2023-02-08T18:14:55Z", "groups": [], "user_permissions": []}}, {"model": "contenttypes.contenttype", "pk": 1, "fields": {"app_label": "admin", "model": "logentry"}}, {"model": "contenttypes.contenttype", "pk": 2, "fields": {"app_label": "auth", "model": "permission"}}, {"model": "contenttypes.contenttype", "pk": 3, "fields": {"app_label": "auth", "model": "group"}}, {"model": "contenttypes.contenttype", "pk": 4, "fields": {"app_label": "auth", "model": "user"}}, {"model": "contenttypes.contenttype", "pk": 5, "fields": {"app_label": "contenttypes", "model": "contenttype"}}, {"model": "contenttypes.contenttype", "pk": 6, "fields": {"app_label": "sessions", "model": "session"}}, {"model": "contenttypes.contenttype", "pk": 7, "fields": {"app_label": "api", "model": "anime"}}, {"model": "contenttypes.contenttype", "pk": 8, "fields": {"app_label": "berita", "model": "news"}}, {"model": "contenttypes.contenttype", "pk": 9, "fields": {"app_label": "api", "model": "berita"}}, {"model": "sessions.session", "pk": "mqz9c8igyl254rlygvqai08fwzsp5utt", "fields": {"session_data": ".eJxVjMEOwiAQRP-FsyFFoAsevfcbyLK7StXQpLQn47_bJj3ocea9mbdKuC4lrU3mNLK6KKNOv11GekrdAT-w3idNU13mMetd0QdtephYXtfD_Tso2Mq2Fh8hULTZWROIepSOTHQAZJyAuYkHOYfAlpGttxYpo9uy6ZlyB6Q-X-JMODs:1pPoyS:pV1jC5c_dNzMHBrlq4fhwrGuKcP38toJWxL-1Yd5r_Q", "expire_date": "2023-02-22T18:15:16.490Z"}}, {"model": "api.anime", "pk": 1, "fields": {"mal_id": 22199, "anime_title": "Akame ga Kill !", "anime_score": "7.47", "airing_time": "Summer 2014", "studio": "White Fox", "slug": "akame-ga-kill", "updated": "2023-02-13T07:27:02.978Z", "created": "2023-02-13T07:27:02.978Z"}}, {"model": "api.anime", "pk": 2, "fields": {"mal_id": 6987, "anime_title": "Aki-Sora", "anime_score": "5.89", "airing_time": "Fall 2009", "studio": "Hoods Entertainment", "slug": "aki-sora", "updated": "2023-02-13T07:28:37.405Z", "created": "2023-02-13T07:28:37.405Z"}}, {"model": "api.anime", "pk": 3, "fields": {"mal_id": 8577, "anime_title": "Aki-Sora - Yume no Naka", "anime_score": "6.00", "airing_time": "Summer 2010", "studio": "Hoods Entertainment", "slug": "aki-sora-yume-no-naka", "updated": "2023-02-13T07:29:42.436Z", "created": "2023-02-13T07:29:42.436Z"}}, {"model": "api.anime", "pk": 4, "fields": {"mal_id": 10490, "anime_title": "Blood C", "anime_score": "6.53", "airing_time": "Summer 2011", "studio": "Production I.G", "slug": "blood-c", "updated": "2023-02-13T07:31:24.511Z", "created": "2023-02-13T07:31:24.511Z"}}, {"model": "api.anime", "pk": 5, "fields": {"mal_id": 10681, "anime_title": "Blood C - The Last Dark", "anime_score": "7.17", "airing_time": "Spring 2012", "studio": "Production I.G", "slug": "blood-c-the-last-dark", "updated": "2023-02-13T07:32:46.494Z", "created": "2023-02-13T07:32:46.494Z"}}, {"model": "api.anime", "pk": 8, "fields": {"mal_id": 6969, "anime_title": "Dummy Test Insert From API View", "anime_score": "4.50", "airing_time": "Summer 1927", "studio": "Pornhub", "slug": "dummy-test-insert-from-api-view", "updated": "2023-02-13T11:42:33.696Z", "created": "2023-02-13T11:42:33.696Z"}}, {"model": "api.anime", "pk": 9, "fields": {"mal_id": 6970, "anime_title": "Data di update melalui API View", "anime_score": "4.50", "airing_time": "Summer 1927", "studio": "Pornhub", "slug": "data-di-update-melalui-api-view", "updated": "2023-02-13T12:35:46.978Z", "created": "2023-02-13T11:47:38.584Z"}}, {"model": "api.anime", "pk": 10, "fields": {"mal_id": 38790, "anime_title": "Itai no wa Iya nano de Bougyoryoku ni Kyokufuri Shitai to Omoimasu", "anime_score": "7.56", "airing_time": "Winter 2020", "studio": "SILVER LINK.", "slug": "itai-no-wa-iya-nano-de-bougyoryoku-ni-kyokufuri-shitai-to-omoimasu", "updated": "2023-02-13T12:46:10.041Z", "created": "2023-02-13T12:46:10.041Z"}}, {"model": "api.anime", "pk": 11, "fields": {"mal_id": 1575, "anime_title": "Code Geass R1 - Hangyaku no Lelouch", "anime_score": "8.70", "airing_time": "Fall 2006", "studio": "Sunrise", "slug": "code-geass-r1-hangyaku-no-lelouch", "updated": "2023-02-13T12:47:24.331Z", "created": "2023-02-13T12:47:24.331Z"}}, {"model": "api.anime", "pk": 12, "fields": {"mal_id": 2904, "anime_title": "Code Geass R2 - Hangyaku no Lelouch", "anime_score": "8.91", "airing_time": "Spring 2008", "studio": "Sunrise", "slug": "code-geass-r2-hangyaku-no-lelouch", "updated": "2023-02-13T12:48:13.805Z", "created": "2023-02-13T12:48:13.805Z"}}, {"model": "api.anime", "pk": 13, "fields": {"mal_id": 8888, "anime_title": "Code Geass Boukoku no Akito 1 (Yokuryuu wa Maiorita)", "anime_score": "7.36", "airing_time": "Summer 2012", "studio": "Sunrise", "slug": "code-geass-boukoku-no-akito-1-yokuryuu-wa-maiorita", "updated": "2023-02-13T12:49:32.283Z", "created": "2023-02-13T12:49:32.283Z"}}, {"model": "api.anime", "pk": 14, "fields": {"mal_id": 15197, "anime_title": "Code Geass Boukoku no Akito 2 (Hikisakareshi Yokuryuu)", "anime_score": "7.48", "airing_time": "Summer 2013", "studio": "Sunrise", "slug": "code-geass-boukoku-no-akito-2-hikisakareshi-yokuryuu", "updated": "2023-02-13T12:50:18.272Z", "created": "2023-02-13T12:50:18.272Z"}}, {"model": "api.anime", "pk": 15, "fields": {"mal_id": 15199, "anime_title": "Code Geass Boukoku no Akito 3 (Kagayaku Mono Ten yori Otsu)", "anime_score": "7.29", "airing_time": "Spring 2015", "studio": "Sunrise", "slug": "code-geass-boukoku-no-akito-3-kagayaku-mono-ten-yori-otsu", "updated": "2023-02-13T12:51:01.692Z", "created": "2023-02-13T12:51:01.692Z"}}, {"model": "api.anime", "pk": 16, "fields": {"mal_id": 15201, "anime_title": "Code Geass Boukoku no Akito 4 (Nikushimi no Kioku kara)", "anime_score": "7.23", "airing_time": "Summer 2015", "studio": "Sunrise", "slug": "code-geass-boukoku-no-akito-4-nikushimi-no-kioku-kara", "updated": "2023-02-13T12:51:58.444Z", "created": "2023-02-13T12:51:58.444Z"}}, {"model": "api.anime", "pk": 17, "fields": {"mal_id": 30711, "anime_title": "Code Geass Boukoku no Akito 5 (Itoshiki Mono-tachi e)", "anime_score": "7.13", "airing_time": "Winter 2016", "studio": "Sunrise", "slug": "code-geass-boukoku-no-akito-5-itoshiki-mono-tachi-e", "updated": "2023-02-13T12:52:39.054Z", "created": "2023-02-13T12:52:39.054Z"}}, {"model": "api.anime", "pk": 18, "fields": {"mal_id": 34437, "anime_title": "Code Geass Fukkatsu no Lelouch", "anime_score": "7.92", "airing_time": "Winter 2019", "studio": "Sunrise", "slug": "code-geass-fukkatsu-no-lelouch", "updated": "2023-02-13T12:53:23.242Z", "created": "2023-02-13T12:53:23.242Z"}}, {"model": "api.anime", "pk": 19, "fields": {"mal_id": 15037, "anime_title": "Corpse Party - Bougyakusareta Tamashii no Jukyou", "anime_score": "6.46", "airing_time": "Summer 2013", "studio": "asread", "slug": "corpse-party-bougyakusareta-tamashii-no-jukyou", "updated": "2023-02-13T12:54:03.219Z", "created": "2023-02-13T12:54:03.219Z"}}, {"model": "api.anime", "pk": 20, "fields": {"mal_id": 13807, "anime_title": "Corpse Party - Missing Footage", "anime_score": "5.99", "airing_time": "Summer 2012", "studio": "asread", "slug": "corpse-party-missing-footage", "updated": "2023-02-13T12:55:12.761Z", "created": "2023-02-13T12:55:12.761Z"}}, {"model": "api.anime", "pk": 21, "fields": {"mal_id": 12549, "anime_title": "Dakara Boku wa, H ga Dekinai", "anime_score": "6.57", "airing_time": "Summer 2012", "studio": "feel.", "slug": "dakara-boku-wa-h-ga-dekinai", "updated": "2023-02-13T12:55:58.478Z", "created": "2023-02-13T12:55:58.478Z"}}, {"model": "api.anime", "pk": 22, "fields": {"mal_id": 35849, "anime_title": "Darling in the FranXX", "anime_score": "7.24", "airing_time": "Winter 2018", "studio": "A-1 Pictures, Trigger, CloverWorks", "slug": "darling-in-the-franxx", "updated": "2023-02-13T12:56:44.425Z", "created": "2023-02-13T12:56:44.425Z"}}, {"model": "api.anime", "pk": 23, "fields": {"mal_id": 15583, "anime_title": "Date A Live 1", "anime_score": "7.17", "airing_time": "Spring 2013", "studio": "AIC PLUS+", "slug": "date-a-live-1", "updated": "2023-02-13T12:57:25.247Z", "created": "2023-02-13T12:57:25.247Z"}}, {"model": "api.anime", "pk": 24, "fields": {"mal_id": 19163, "anime_title": "Date A Live 2", "anime_score": "7.20", "airing_time": "Spring 2014", "studio": "Production IMS", "slug": "date-a-live-2", "updated": "2023-02-13T12:58:01.605Z", "created": "2023-02-13T12:58:01.605Z"}}, {"model": "api.anime", "pk": 25, "fields": {"mal_id": 36633, "anime_title": "Date A Live 3", "anime_score": "7.18", "airing_time": "Winter 2019", "studio": "J.C.Staff", "slug": "date-a-live-3", "updated": "2023-02-13T12:58:38.506Z", "created": "2023-02-13T12:58:38.506Z"}}, {"model": "api.anime", "pk": 26, "fields": {"mal_id": 41461, "anime_title": "Date A Live 4", "anime_score": "7.85", "airing_time": "Spring 2022", "studio": "GEEK TOYS", "slug": "date-a-live-4", "updated": "2023-02-13T13:00:52.309Z", "created": "2023-02-13T13:00:52.309Z"}}, {"model": "api.anime", "pk": 27, "fields": {"mal_id": 24655, "anime_title": "Date A Live Movie: Mayuri Judgement", "anime_score": "7.34", "airing_time": "Summer 2015", "studio": "Production IMS", "slug": "date-a-live-movie-mayuri-judgement", "updated": "2023-02-13T13:01:35.313Z", "created": "2023-02-13T13:01:35.313Z"}}, {"model": "api.anime", "pk": 28, "fields": {"mal_id": 40416, "anime_title": "Date A Bullet 1 - Dead or Bullet's", "anime_score": "7.56", "airing_time": "Summer 2020", "studio": "GEEK TOYS", "slug": "date-a-bullet-1-dead-or-bullets", "updated": "2023-02-13T13:02:36.904Z", "created": "2023-02-13T13:02:36.904Z"}}, {"model": "api.anime", "pk": 29, "fields": {"mal_id": 42423, "anime_title": "Date A Bullet 2 - Queen's or Nightmare", "anime_score": "7.62", "airing_time": "Fall 2020", "studio": "GEEK TOYS", "slug": "date-a-bullet-2-queens-or-nightmare", "updated": "2023-02-13T13:03:25.253Z", "created": "2023-02-13T13:03:25.253Z"}}, {"model": "api.anime", "pk": 30, "fields": {"mal_id": 226, "anime_title": "Elfen Lied", "anime_score": "7.51", "airing_time": "Summer 2004", "studio": "Arms", "slug": "elfen-lied", "updated": "2023-02-13T13:04:33.453Z", "created": "2023-02-13T13:04:33.453Z"}}, {"model": "api.anime", "pk": 31, "fields": {"mal_id": 30, "anime_title": "Neon Genesis Evangelion", "anime_score": "8.34", "airing_time": "Fall 1995", "studio": "GAINAX & Production I.G", "slug": "neon-genesis-evangelion", "updated": "2023-02-13T13:05:19.879Z", "created": "2023-02-13T13:05:19.879Z"}}, {"model": "api.anime", "pk": 32, "fields": {"mal_id": 32, "anime_title": "Neon Genesis Evangelion: The End of Evangelion", "anime_score": "8.55", "airing_time": "Summer 1997", "studio": "GAINAX & Production I.G", "slug": "neon-genesis-evangelion-the-end-of-evangelion", "updated": "2023-02-13T13:05:59.879Z", "created": "2023-02-13T13:05:59.879Z"}}, {"model": "api.anime", "pk": 33, "fields": {"mal_id": 2759, "anime_title": "Evangelion 1.0 You Are (Not) Alone", "anime_score": "8.02", "airing_time": "Summer 2007", "studio": "Khara", "slug": "evangelion-10-you-are-not-alone", "updated": "2023-02-13T13:41:05.644Z", "created": "2023-02-13T13:41:05.644Z"}}, {"model": "api.anime", "pk": 34, "fields": {"mal_id": 3784, "anime_title": "Evangelion 2.0 You Can (Not) Advance", "anime_score": "8.32", "airing_time": "Summer 2009", "studio": "Khara", "slug": "evangelion-20-you-can-not-advance", "updated": "2023-02-13T13:41:54.552Z", "created": "2023-02-13T13:41:54.552Z"}}, {"model": "api.anime", "pk": 35, "fields": {"mal_id": 3785, "anime_title": "Evangelion 3.0 You Can (Not) Redo", "anime_score": "7.62", "airing_time": "Fall 2012", "studio": "Khara", "slug": "evangelion-30-you-can-not-redo", "updated": "2023-02-13T13:42:09.507Z", "created": "2023-02-13T13:42:09.507Z"}}, {"model": "api.anime", "pk": 36, "fields": {"mal_id": 3786, "anime_title": "Evangelion 3.0 + 1.0 Thrice Upon a Time", "anime_score": "8.64", "airing_time": "Winter 2021", "studio": "Khara", "slug": "evangelion-30-10-thrice-upon-a-time", "updated": "2023-02-13T13:42:22.218Z", "created": "2023-02-13T13:42:22.218Z"}}, {"model": "api.anime", "pk": 37, "fields": {"mal_id": 34662, "anime_title": "Fate Apocrypha", "anime_score": "7.18", "airing_time": "Summer 2017", "studio": "A-1 Pictures", "slug": "fate-apocrypha", "updated": "2023-02-13T14:07:25.679Z", "created": "2023-02-13T14:07:25.679Z"}}, {"model": "api.anime", "pk": 38, "fields": {"mal_id": 38085, "anime_title": "Fate Grand Order - Shinsei Entaku Ryouiki Camelot 1 Wandering Agateram", "anime_score": "6.84", "airing_time": "Fall 2020", "studio": "Signal.MD", "slug": "fate-grand-order-shinsei-entaku-ryouiki-camelot-1-wandering-agateram", "updated": "2023-02-13T14:07:44.908Z", "created": "2023-02-13T14:07:44.908Z"}}, {"model": "api.anime", "pk": 39, "fields": {"mal_id": 38086, "anime_title": "Fate Grand Order - Shinsei Entaku Ryouiki Camelot 2 Paladin Agateram", "anime_score": "7.58", "airing_time": "Spring 2021", "studio": "Production I.G", "slug": "fate-grand-order-shinsei-entaku-ryouiki-camelot-2-paladin-agateram", "updated": "2023-02-13T14:07:58.228Z", "created": "2023-02-13T14:07:58.228Z"}}, {"model": "api.anime", "pk": 40, "fields": {"mal_id": 38084, "anime_title": "Fate Grand Order - Zettai Majuu Sensen Babylonia", "anime_score": "7.94", "airing_time": "Fall 2019", "studio": "CloverWorks", "slug": "fate-grand-order-zettai-majuu-sensen-babylonia", "updated": "2023-02-13T14:08:15.206Z", "created": "2023-02-13T14:08:15.206Z"}}, {"model": "api.anime", "pk": 41, "fields": {"mal_id": 41497, "anime_title": "Fate Grand Order - Shuukyoku Tokuiten Kani Jikan Shinden Solomon", "anime_score": "8.09", "airing_time": "Summer 2021", "studio": "CloverWorks", "slug": "fate-grand-order-shuukyoku-tokuiten-kani-jikan-shinden-solomon", "updated": "2023-02-13T14:08:32.980Z", "created": "2023-02-13T14:08:32.980Z"}}, {"model": "api.anime", "pk": 42, "fields": {"mal_id": 356, "anime_title": "Fate Stay Night", "anime_score": "7.29", "airing_time": "Winter 2006", "studio": "Studio Deen", "slug": "fate-stay-night", "updated": "2023-02-13T14:08:46.248Z", "created": "2023-02-13T14:08:46.248Z"}}, {"model": "api.anime", "pk": 43, "fields": {"mal_id": 22297, "anime_title": "Fate Stay Night - Unlimited Blade Works 1", "anime_score": "8.19", "airing_time": "Fall 2014", "studio": "ufotable", "slug": "fate-stay-night-unlimited-blade-works-1", "updated": "2023-02-13T14:08:58.840Z", "created": "2023-02-13T14:08:58.840Z"}}, {"model": "api.anime", "pk": 44, "fields": {"mal_id": 28701, "anime_title": "Fate Stay Night - Unlimited Blade Works 2", "anime_score": "8.32", "airing_time": "Spring 2015", "studio": "ufotable", "slug": "fate-stay-night-unlimited-blade-works-2", "updated": "2023-02-13T14:09:11.919Z", "created": "2023-02-13T14:09:11.919Z"}}, {"model": "api.anime", "pk": 45, "fields": {"mal_id": 25537, "anime_title": "Fate Stay Night - Heaven's Feel 1 Pressage Flower", "anime_score": "8.20", "airing_time": "Fall 2017", "studio": "ufotable", "slug": "fate-stay-night-heavens-feel-1-pressage-flower", "updated": "2023-02-13T14:09:27.701Z", "created": "2023-02-13T14:09:27.701Z"}}, {"model": "api.anime", "pk": 46, "fields": {"mal_id": 33049, "anime_title": "Fate Stay Night - Heaven's Feel 2 Lost Butterfly", "anime_score": "8.54", "airing_time": "Winter 2019", "studio": "ufotable", "slug": "fate-stay-night-heavens-feel-2-lost-butterfly", "updated": "2023-02-13T14:09:40.757Z", "created": "2023-02-13T14:09:40.757Z"}}, {"model": "api.anime", "pk": 47, "fields": {"mal_id": 33050, "anime_title": "Fate Stay Night - Heaven's Feel 3 Spring Song", "anime_score": "8.72", "airing_time": "Summer 2020", "studio": "ufotable", "slug": "fate-stay-night-heavens-feel-3-spring-song", "updated": "2023-02-13T14:09:56.241Z", "created": "2023-02-13T14:09:56.241Z"}}, {"model": "api.anime", "pk": 48, "fields": {"mal_id": 10087, "anime_title": "Fate Zero 1", "anime_score": "8.30", "airing_time": "Fall 2011", "studio": "ufotable", "slug": "fate-zero-1", "updated": "2023-02-13T14:10:08.673Z", "created": "2023-02-13T14:10:08.673Z"}}, {"model": "api.anime", "pk": 49, "fields": {"mal_id": 11741, "anime_title": "Fate Zero 2", "anime_score": "8.57", "airing_time": "Spring 2012", "studio": "ufotable", "slug": "fate-zero-2", "updated": "2023-02-13T14:10:21.588Z", "created": "2023-02-13T14:10:21.588Z"}}, {"model": "api.anime", "pk": 50, "fields": {"mal_id": 48760, "anime_title": "Gaikotsu Kishi-sama, Tadaima Isekai e Odekakechuu", "anime_score": "7.23", "airing_time": "Spring 2022", "studio": "Studio Kai, HORNETS", "slug": "gaikotsu-kishi-sama-tadaima-isekai-e-odekakechuu", "updated": "2023-02-13T14:10:33.780Z", "created": "2023-02-13T14:10:33.780Z"}}, {"model": "api.anime", "pk": 51, "fields": {"mal_id": 2775, "anime_title": "Genocyber", "anime_score": "5.81", "airing_time": "Winter 1994", "studio": "Artmic", "slug": "genocyber", "updated": "2023-02-13T14:10:47.672Z", "created": "2023-02-13T14:10:47.672Z"}}, {"model": "api.anime", "pk": 52, "fields": {"mal_id": 43, "anime_title": "Koukaku Kidoutai", "anime_score": "8.28", "airing_time": "Fall 1995", "studio": "Production I.G", "slug": "koukaku-kidoutai", "updated": "2023-02-13T14:25:48.555Z", "created": "2023-02-13T14:25:48.555Z"}}, {"model": "api.anime", "pk": 53, "fields": {"mal_id": 468, "anime_title": "Koukaku Kidoutai 2 - Innocence", "anime_score": "7.80", "airing_time": "Winter 2004", "studio": "Production I.G", "slug": "koukaku-kidoutai-2-innocence", "updated": "2023-02-13T14:26:06.960Z", "created": "2023-02-13T14:26:06.960Z"}}, {"model": "api.anime", "pk": 54, "fields": {"mal_id": 37349, "anime_title": "Goblin Slayer", "anime_score": "7.42", "airing_time": "Fall 2018", "studio": "White Fox", "slug": "goblin-slayer", "updated": "2023-02-13T14:26:22.486Z", "created": "2023-02-13T14:26:22.486Z"}}, {"model": "api.anime", "pk": 55, "fields": {"mal_id": 39576, "anime_title": "Goblin Slayer - Goblin's Crown", "anime_score": "7.25", "airing_time": "Winter 2020", "studio": "White Fox", "slug": "goblin-slayer-goblins-crown", "updated": "2023-02-13T14:26:40.890Z", "created": "2023-02-13T14:26:40.890Z"}}, {"model": "api.anime", "pk": 56, "fields": {"mal_id": 268, "anime_title": "Golden Boy", "anime_score": "8.02", "airing_time": "Fall 1996", "studio": "APPP", "slug": "golden-boy", "updated": "2023-02-13T14:26:59.502Z", "created": "2023-02-13T14:26:59.502Z"}}, {"model": "api.anime", "pk": 57, "fields": {"mal_id": 38101, "anime_title": "Gotoubun no Hanayome (Season 1)", "anime_score": "7.68", "airing_time": "Winter 2019", "studio": "Tezuka Productions", "slug": "gotoubun-no-hanayome-season-1", "updated": "2023-02-13T14:29:28.853Z", "created": "2023-02-13T14:29:28.853Z"}}, {"model": "api.anime", "pk": 58, "fields": {"mal_id": 39783, "anime_title": "Gotoubun no Hanayome (Season 2)", "anime_score": "8.12", "airing_time": "Winter 2021", "studio": "Bilbury Animation Studios", "slug": "gotoubun-no-hanayome-season-2", "updated": "2023-02-13T14:29:43.044Z", "created": "2023-02-13T14:29:43.044Z"}}, {"model": "api.anime", "pk": 59, "fields": {"mal_id": 10793, "anime_title": "Guilty Crown", "anime_score": "7.44", "airing_time": "Fall 2011", "studio": "Production I.G", "slug": "guilty-crown", "updated": "2023-02-13T14:30:06.880Z", "created": "2023-02-13T14:30:06.880Z"}}, {"model": "api.anime", "pk": 60, "fields": {"mal_id": 41911, "anime_title": "Hanyou no Yashahime - Sengoku Otogizoushi", "anime_score": "6.72", "airing_time": "Fall 2020", "studio": "Sunrise", "slug": "hanyou-no-yashahime-sengoku-otogizoushi", "updated": "2023-02-13T14:31:06.542Z", "created": "2023-02-13T14:31:06.542Z"}}, {"model": "api.anime", "pk": 61, "fields": {"mal_id": 48505, "anime_title": "Hanyou no Yashahime - Sengoku Otogizoushi Ni Shou", "anime_score": "7.09", "airing_time": "Fall 2021", "studio": "Sunrise", "slug": "hanyou-no-yashahime-sengoku-otogizoushi-ni-shou", "updated": "2023-02-13T14:31:17.608Z", "created": "2023-02-13T14:31:17.608Z"}}, {"model": "api.anime", "pk": 62, "fields": {"mal_id": 15809, "anime_title": "Hataraku Maou-sama", "anime_score": "7.78", "airing_time": "Spring 2013", "studio": "White Fox", "slug": "hataraku-maou-sama", "updated": "2023-02-13T14:31:28.443Z", "created": "2023-02-13T14:31:28.443Z"}}, {"model": "api.anime", "pk": 63, "fields": {"mal_id": 48413, "anime_title": "Hataraku Maou-sama 2", "anime_score": "7.78", "airing_time": "Summer 2022", "studio": "3Hz", "slug": "hataraku-maou-sama-2", "updated": "2023-02-13T14:31:39.716Z", "created": "2023-02-13T14:31:39.716Z"}}, {"model": "api.anime", "pk": 64, "fields": {"mal_id": 270, "anime_title": "Hellsing", "anime_score": "7.49", "airing_time": "Fall 2001", "studio": "Gonzo", "slug": "hellsing", "updated": "2023-02-13T14:31:51.212Z", "created": "2023-02-13T14:31:51.212Z"}}, {"model": "api.anime", "pk": 65, "fields": {"mal_id": 11077, "anime_title": "Hellsing The Dawn", "anime_score": "7.15", "airing_time": "Summer 2011", "studio": "Graphinica", "slug": "hellsing-the-dawn", "updated": "2023-02-13T14:32:05.686Z", "created": "2023-02-13T14:32:05.686Z"}}, {"model": "api.anime", "pk": 66, "fields": {"mal_id": 777, "anime_title": "Hellsing Ultimate", "anime_score": "8.36", "airing_time": "Winter 2006", "studio": "Madhouse, Satelight, Graphinica", "slug": "hellsing-ultimate", "updated": "2023-02-13T14:32:17.575Z", "created": "2023-02-13T14:32:17.575Z"}}, {"model": "api.anime", "pk": 67, "fields": {"mal_id": 11617, "anime_title": "High School DxD 1", "anime_score": "7.35", "airing_time": "Winter 2012", "studio": "TNK", "slug": "high-school-dxd-1", "updated": "2023-02-13T14:32:29.807Z", "created": "2023-02-13T14:32:29.807Z"}}, {"model": "api.anime", "pk": 68, "fields": {"mal_id": 15451, "anime_title": "High School DxD 2 New", "anime_score": "7.49", "airing_time": "Summer 2013", "studio": "TNK", "slug": "high-school-dxd-2-new", "updated": "2023-02-13T14:32:41.171Z", "created": "2023-02-13T14:32:41.171Z"}}, {"model": "api.anime", "pk": 69, "fields": {"mal_id": 24703, "anime_title": "High School DxD 3 Born", "anime_score": "7.43", "airing_time": "Spring 2015", "studio": "TNK", "slug": "high-school-dxd-3-born", "updated": "2023-02-13T14:32:54.557Z", "created": "2023-02-13T14:32:54.557Z"}}, {"model": "api.anime", "pk": 70, "fields": {"mal_id": 34281, "anime_title": "High School DxD 4 Hero", "anime_score": "7.26", "airing_time": "Spring 2018", "studio": "PASSIONE", "slug": "high-school-dxd-4-hero", "updated": "2023-02-13T14:33:10.111Z", "created": "2023-02-13T14:33:10.111Z"}}, {"model": "api.anime", "pk": 71, "fields": {"mal_id": 8074, "anime_title": "Highschool Of The Dead", "anime_score": "7.08", "airing_time": "Summer 2010", "studio": "Madhouse", "slug": "highschool-of-the-dead", "updated": "2023-02-14T12:07:07.338Z", "created": "2023-02-14T12:07:07.338Z"}}, {"model": "api.anime", "pk": 72, "fields": {"mal_id": 934, "anime_title": "Higurashi no Naku Koro ni", "anime_score": "7.90", "airing_time": "Spring 2006", "studio": "Studio Deen", "slug": "higurashi-no-naku-koro-ni", "updated": "2023-02-14T12:08:30.083Z", "created": "2023-02-14T12:08:30.083Z"}}, {"model": "api.anime", "pk": 73, "fields": {"mal_id": 1889, "anime_title": "Higurashi no Naku Koro ni Kai", "anime_score": "8.37", "airing_time": "Winter 2007", "studio": "Geneon Universal Entertainment", "slug": "higurashi-no-naku-koro-ni-kai", "updated": "2023-02-14T12:08:45.557Z", "created": "2023-02-14T12:08:45.557Z"}}, {"model": "api.anime", "pk": 74, "fields": {"mal_id": 3652, "anime_title": "Higurashi no Naku Koro ni Rei", "anime_score": "7.41", "airing_time": "Winter 2009", "studio": "Studio Deen", "slug": "higurashi-no-naku-koro-ni-rei", "updated": "2023-02-14T12:08:59.895Z", "created": "2023-02-14T12:08:59.895Z"}}, {"model": "api.anime", "pk": 75, "fields": {"mal_id": 41006, "anime_title": "Higurashi no Naku Koro ni Gou", "anime_score": "7.20", "airing_time": "Fall 2020", "studio": "PASSIONE", "slug": "higurashi-no-naku-koro-ni-gou", "updated": "2023-02-14T12:09:15.211Z", "created": "2023-02-14T12:09:15.211Z"}}, {"model": "api.anime", "pk": 76, "fields": {"mal_id": 48488, "anime_title": "Higurashi no Naku Koro ni Sotsu", "anime_score": "6.77", "airing_time": "Summer 2021", "studio": "PASSIONE", "slug": "higurashi-no-naku-koro-ni-sotsu", "updated": "2023-02-14T12:09:31.320Z", "created": "2023-02-14T12:09:31.320Z"}}, {"model": "api.anime", "pk": 77, "fields": {"mal_id": 8277, "anime_title": "Hyakka Ryouran - Samurai Girls", "anime_score": "6.78", "airing_time": "Fall 2010", "studio": "Arms", "slug": "hyakka-ryouran-samurai-girls", "updated": "2023-02-14T12:09:59.051Z", "created": "2023-02-14T12:09:59.051Z"}}, {"model": "api.anime", "pk": 78, "fields": {"mal_id": 15377, "anime_title": "Hyakka Ryouran - Samurai Bride", "anime_score": "6.73", "airing_time": "Spring 2013", "studio": "Arms", "slug": "hyakka-ryouran-samurai-bride", "updated": "2023-02-14T12:10:30.233Z", "created": "2023-02-14T12:10:30.233Z"}}, {"model": "api.anime", "pk": 79, "fields": {"mal_id": 9041, "anime_title": "Infinite Stratos 1", "anime_score": "6.65", "airing_time": "Winter 2011", "studio": "8bit", "slug": "infinite-stratos-1", "updated": "2023-02-14T12:10:43.235Z", "created": "2023-02-14T12:10:43.235Z"}}, {"model": "api.anime", "pk": 80, "fields": {"mal_id": 10794, "anime_title": "Infinite Stratos 1 Encore - Koi ni Kogareru Rokujuusou", "anime_score": "6.86", "airing_time": "Fall 2011", "studio": "8bit", "slug": "infinite-stratos-1-encore-koi-ni-kogareru-rokujuusou", "updated": "2023-02-14T12:15:44.589Z", "created": "2023-02-14T12:15:44.589Z"}}, {"model": "api.anime", "pk": 81, "fields": {"mal_id": 18247, "anime_title": "Infinite Stratos 2", "anime_score": "6.48", "airing_time": "Fall 2013", "studio": "8bit", "slug": "infinite-stratos-2", "updated": "2023-02-14T12:16:04.550Z", "created": "2023-02-14T12:16:04.550Z"}}, {"model": "api.anime", "pk": 82, "fields": {"mal_id": 20045, "anime_title": "Infinite Stratos 2 - Hitonatsu no Omoide", "anime_score": "6.88", "airing_time": "Fall 2013", "studio": "8bit", "slug": "infinite-stratos-2-hitonatsu-no-omoide", "updated": "2023-02-14T12:16:20.794Z", "created": "2023-02-14T12:16:20.794Z"}}, {"model": "api.anime", "pk": 83, "fields": {"mal_id": 21653, "anime_title": "Infinite Stratos 2 - World Purge-hen", "anime_score": "6.88", "airing_time": "Fall 2014", "studio": "8bit", "slug": "infinite-stratos-2-world-purge-hen", "updated": "2023-02-14T12:16:43.079Z", "created": "2023-02-14T12:16:43.079Z"}}, {"model": "api.anime", "pk": 84, "fields": {"mal_id": 33242, "anime_title": "Infinite Stratos 2 - Infinite Wedding", "anime_score": "6.39", "airing_time": "Spring 2016", "studio": "8bit", "slug": "infinite-stratos-2-infinite-wedding", "updated": "2023-02-14T12:18:18.226Z", "created": "2023-02-14T12:18:18.226Z"}}, {"model": "api.anime", "pk": 85, "fields": {"mal_id": 249, "anime_title": "InuYasha", "anime_score": "7.85", "airing_time": "Fall 2000", "studio": "Sunrise", "slug": "inuyasha", "updated": "2023-02-14T12:18:34.263Z", "created": "2023-02-14T12:18:34.263Z"}}, {"model": "api.anime", "pk": 86, "fields": {"mal_id": 452, "anime_title": "InuYasha Movie 1 - Toki wo Koeru Omoi", "anime_score": "7.56", "airing_time": "Fall 2001", "studio": "Sunrise", "slug": "inuyasha-movie-1-toki-wo-koeru-omoi", "updated": "2023-02-14T12:20:26.350Z", "created": "2023-02-14T12:20:26.350Z"}}, {"model": "api.anime", "pk": 87, "fields": {"mal_id": 450, "anime_title": "InuYasha Movie 2 - Kagami no Naka no Mugenjo", "anime_score": "7.67", "airing_time": "Fall 2002", "studio": "Sunrise", "slug": "inuyasha-movie-2-kagami-no-naka-no-mugenjo", "updated": "2023-02-14T12:20:41.197Z", "created": "2023-02-14T12:20:41.197Z"}}, {"model": "api.anime", "pk": 88, "fields": {"mal_id": 451, "anime_title": "InuYasha Movie 3 - Tenka Hadou no Ken", "anime_score": "7.80", "airing_time": "Fall 2003", "studio": "Sunrise", "slug": "inuyasha-movie-3-tenka-hadou-no-ken", "updated": "2023-02-14T12:20:58.302Z", "created": "2023-02-14T12:20:58.302Z"}}, {"model": "api.anime", "pk": 89, "fields": {"mal_id": 449, "anime_title": "InuYasha Movie 4 - Guren no Houraijima", "anime_score": "7.55", "airing_time": "Fall 2004", "studio": "Sunrise", "slug": "inuyasha-movie-4-guren-no-houraijima", "updated": "2023-02-14T12:21:11.252Z", "created": "2023-02-14T12:21:11.252Z"}}, {"model": "api.anime", "pk": 90, "fields": {"mal_id": 6811, "anime_title": "InuYasha The Final Act", "anime_score": "8.20", "airing_time": "Fall 2009", "studio": "Sunrise", "slug": "inuyasha-the-final-act", "updated": "2023-02-14T12:21:23.585Z", "created": "2023-02-14T12:21:23.585Z"}}, {"model": "api.anime", "pk": 91, "fields": {"mal_id": 44524, "anime_title": "Isekai Meikyuu de Harem wo", "anime_score": "6.61", "airing_time": "Summer 2022", "studio": "Passione", "slug": "isekai-meikyuu-de-harem-wo", "updated": "2023-02-14T12:21:40.082Z", "created": "2023-02-14T12:21:40.082Z"}}, {"model": "api.anime", "pk": 92, "fields": {"mal_id": 635, "anime_title": "Juubee-chan 1: Lovely Gantai no Himitsu", "anime_score": "6.67", "airing_time": "Spring 1999", "studio": "Madhouse", "slug": "juubee-chan-1-lovely-gantai-no-himitsu", "updated": "2023-02-14T12:22:16.172Z", "created": "2023-02-14T12:22:16.172Z"}}, {"model": "api.anime", "pk": 93, "fields": {"mal_id": 636, "anime_title": "Juubee-chan 2: Siberia Yagyuu no Gyakushuu", "anime_score": "6.85", "airing_time": "Winter 2004", "studio": "Madhouse", "slug": "juubee-chan-2-siberia-yagyuu-no-gyakushuu", "updated": "2023-02-14T12:22:31.481Z", "created": "2023-02-14T12:22:31.481Z"}}, {"model": "api.anime", "pk": 94, "fields": {"mal_id": 40750, "anime_title": "Kaifuku Jutsushi no Yarinaoshi", "anime_score": "6.33", "airing_time": "Winter 2021", "studio": "TNK", "slug": "kaifuku-jutsushi-no-yarinaoshi", "updated": "2023-02-14T12:22:47.236Z", "created": "2023-02-14T12:22:47.236Z"}}, {"model": "api.anime", "pk": 95, "fields": {"mal_id": 40839, "anime_title": "Kanojo Okarishimasu", "anime_score": "7.23", "airing_time": "Summer 2020", "studio": "TMS Entertainment", "slug": "kanojo-okarishimasu", "updated": "2023-02-14T12:23:06.297Z", "created": "2023-02-14T12:23:06.297Z"}}, {"model": "api.anime", "pk": 96, "fields": {"mal_id": 42963, "anime_title": "Kanojo Okarishimasu 2", "anime_score": "6.88", "airing_time": "Summer 2022", "studio": "TMS Entertainment", "slug": "kanojo-okarishimasu-2", "updated": "2023-02-14T12:23:24.036Z", "created": "2023-02-14T12:23:24.036Z"}}, {"model": "api.anime", "pk": 97, "fields": {"mal_id": 45613, "anime_title": "Kawaii dake ja Nai Shikimori-san", "anime_score": "6.69", "airing_time": "Spring 2022", "studio": "Doga Kobo", "slug": "kawaii-dake-ja-nai-shikimori-san", "updated": "2023-02-14T12:23:37.290Z", "created": "2023-02-14T12:23:37.290Z"}}, {"model": "api.anime", "pk": 98, "fields": {"mal_id": 1606, "anime_title": "Kekkaishi", "anime_score": "7.60", "airing_time": "Fall 2006", "studio": "Sunrise", "slug": "kekkaishi", "updated": "2023-02-14T12:23:57.859Z", "created": "2023-02-14T12:23:57.859Z"}}, {"model": "api.anime", "pk": 99, "fields": {"mal_id": 40908, "anime_title": "Kemono Jihen", "anime_score": "7.42", "airing_time": "Winter 2021", "studio": "Ajia-Do", "slug": "kemono-jihen", "updated": "2023-02-14T12:24:13.335Z", "created": "2023-02-14T12:24:13.335Z"}}, {"model": "api.anime", "pk": 100, "fields": {"mal_id": 34964, "anime_title": "Killing Bites", "anime_score": "6.58", "airing_time": "Winter 2018", "studio": "LIDENFILMS", "slug": "killing-bites", "updated": "2023-02-14T12:24:29.400Z", "created": "2023-02-14T12:24:29.400Z"}}, {"model": "api.anime", "pk": 101, "fields": {"mal_id": 38000, "anime_title": "Kimetsu no Yaiba 1", "anime_score": "8.55", "airing_time": "Spring 2019", "studio": "Ufotable", "slug": "kimetsu-no-yaiba-1", "updated": "2023-02-14T12:25:23.999Z", "created": "2023-02-14T12:25:23.999Z"}}, {"model": "api.anime", "pk": 102, "fields": {"mal_id": 49926, "anime_title": "Kimetsu no Yaiba 1 - Mugen Ressha hen", "anime_score": "8.39", "airing_time": "Fall 2021", "studio": "Ufotable", "slug": "kimetsu-no-yaiba-1-mugen-ressha-hen", "updated": "2023-02-14T12:25:40.394Z", "created": "2023-02-14T12:25:40.394Z"}}, {"model": "api.anime", "pk": 103, "fields": {"mal_id": 47778, "anime_title": "Kimetsu no Yaiba 2 - Yuukaku hen", "anime_score": "8.87", "airing_time": "Winter 2022", "studio": "Ufotable", "slug": "kimetsu-no-yaiba-2-yuukaku-hen", "updated": "2023-02-14T12:25:55.828Z", "created": "2023-02-14T12:25:55.828Z"}}, {"model": "api.anime", "pk": 104, "fields": {"mal_id": 51213, "anime_title": "Kinsou no Vermeil to Mahou Sekai no Tsukisusumu", "anime_score": "7.33", "airing_time": "Summer 2022", "studio": "Staple Entertainment", "slug": "kinsou-no-vermeil-to-mahou-sekai-no-tsukisusumu", "updated": "2023-02-14T12:26:10.322Z", "created": "2023-02-14T12:26:10.322Z"}}, {"model": "api.anime", "pk": 105, "fields": {"mal_id": 22535, "anime_title": "Kiseijuu Sei no Kakuritsu", "anime_score": "8.35", "airing_time": "Fall 2014", "studio": "Madhouse", "slug": "kiseijuu-sei-no-kakuritsu", "updated": "2023-02-14T12:26:24.798Z", "created": "2023-02-14T12:26:24.798Z"}}, {"model": "api.anime", "pk": 106, "fields": {"mal_id": 30381, "anime_title": "Kono Subarashii Sekai ni Syukufuku Wo 1", "anime_score": "8.12", "airing_time": "Winter 2016", "studio": "Studio Deen", "slug": "kono-subarashii-sekai-ni-syukufuku-wo-1", "updated": "2023-02-14T12:26:41.995Z", "created": "2023-02-14T12:26:41.995Z"}}, {"model": "api.anime", "pk": 107, "fields": {"mal_id": 32937, "anime_title": "Kono Subarashii Sekai ni Syukufuku Wo 2", "anime_score": "8.28", "airing_time": "Winter 2017", "studio": "Studio Deen", "slug": "kono-subarashii-sekai-ni-syukufuku-wo-2", "updated": "2023-02-14T12:26:56.506Z", "created": "2023-02-14T12:26:56.506Z"}}, {"model": "api.anime", "pk": 108, "fields": {"mal_id": 38040, "anime_title": "Konosuba Movie - Kurenai Densetsu", "anime_score": "8.47", "airing_time": "Summer 2019", "studio": "J.C.Staff", "slug": "konosuba-movie-kurenai-densetsu", "updated": "2023-02-14T12:27:10.810Z", "created": "2023-02-14T12:27:10.810Z"}}, {"model": "api.anime", "pk": 109, "fields": {"mal_id": 8841, "anime_title": "Kore wa Zombie Desu ka 1", "anime_score": "7.37", "airing_time": "Winter 2011", "studio": "Studio Deen", "slug": "kore-wa-zombie-desu-ka-1", "updated": "2023-02-14T12:27:31.313Z", "created": "2023-02-14T12:27:31.313Z"}}, {"model": "api.anime", "pk": 110, "fields": {"mal_id": 10790, "anime_title": "Kore wa Zombie Desu ka 2", "anime_score": "7.51", "airing_time": "Spring 2012", "studio": "Studio Deen", "slug": "kore-wa-zombie-desu-ka-2", "updated": "2023-02-14T12:27:45.142Z", "created": "2023-02-14T12:27:45.142Z"}}, {"model": "api.anime", "pk": 111, "fields": {"mal_id": 10620, "anime_title": "Mirai Nikki", "anime_score": "7.45", "airing_time": "Fall 2011", "studio": "asread", "slug": "mirai-nikki", "updated": "2023-02-14T12:28:00.091Z", "created": "2023-02-14T12:28:00.091Z"}}, {"model": "api.anime", "pk": 112, "fields": {"mal_id": 14833, "anime_title": "Maoyuu Maou Yuusha", "anime_score": "7.26", "airing_time": "Winter 2013", "studio": "Arms", "slug": "maoyuu-maou-yuusha", "updated": "2023-02-14T12:28:13.971Z", "created": "2023-02-14T12:28:13.971Z"}}, {"model": "api.anime", "pk": 113, "fields": {"mal_id": 5081, "anime_title": "Bakemonogatari", "anime_score": "8.34", "airing_time": "Summer 2009", "studio": "SHAFT", "slug": "bakemonogatari", "updated": "2023-02-14T12:28:27.733Z", "created": "2023-02-14T12:28:27.733Z"}}, {"model": "api.anime", "pk": 114, "fields": {"mal_id": 9260, "anime_title": "Kizumonogatari 1 - Tekketsu hen", "anime_score": "8.38", "airing_time": "Winter 2016", "studio": "SHAFT", "slug": "kizumonogatari-1-tekketsu-hen", "updated": "2023-02-14T12:28:41.510Z", "created": "2023-02-14T12:28:41.510Z"}}, {"model": "api.anime", "pk": 115, "fields": {"mal_id": 31757, "anime_title": "Kizumonogatari 2 - Nekketsu hen", "anime_score": "8.59", "airing_time": "Summer 2016", "studio": "SHAFT", "slug": "kizumonogatari-2-nekketsu-hen", "updated": "2023-02-14T12:28:55.523Z", "created": "2023-02-14T12:28:55.523Z"}}, {"model": "api.anime", "pk": 116, "fields": {"mal_id": 31758, "anime_title": "Kizumonogatari 3 - Reiketsu hen", "anime_score": "8.80", "airing_time": "Winter 2017", "studio": "SHAFT", "slug": "kizumonogatari-3-reiketsu-hen", "updated": "2023-02-14T12:29:09.067Z", "created": "2023-02-14T12:29:09.067Z"}}, {"model": "api.anime", "pk": 117, "fields": {"mal_id": 32268, "anime_title": "Koyomimonogatari", "anime_score": "7.64", "airing_time": "Winter 2016", "studio": "SHAFT", "slug": "koyomimonogatari", "updated": "2023-02-14T12:29:27.884Z", "created": "2023-02-14T12:29:27.884Z"}}, {"model": "api.anime", "pk": 118, "fields": {"mal_id": 17074, "anime_title": "Monogatari Series 2nd Season", "anime_score": "8.78", "airing_time": "Summer 2013", "studio": "SHAFT", "slug": "monogatari-series-2nd-season", "updated": "2023-02-14T12:29:41.822Z", "created": "2023-02-14T12:29:41.822Z"}}, {"model": "api.anime", "pk": 119, "fields": {"mal_id": 15689, "anime_title": "Nekomonogatari - Kuro", "anime_score": "7.49", "airing_time": "Fall 2012", "studio": "SHAFT", "slug": "nekomonogatari-kuro", "updated": "2023-02-14T12:30:16.431Z", "created": "2023-02-14T12:30:16.431Z"}}, {"model": "api.anime", "pk": 120, "fields": {"mal_id": 11597, "anime_title": "Nisemonogatari", "anime_score": "8.15", "airing_time": "Winter 2012", "studio": "SHAFT", "slug": "nisemonogatari", "updated": "2023-02-14T12:30:31.323Z", "created": "2023-02-14T12:30:31.323Z"}}, {"model": "api.anime", "pk": 121, "fields": {"mal_id": 31181, "anime_title": "Owarimonogatari", "anime_score": "8.46", "airing_time": "Fall 2015", "studio": "SHAFT", "slug": "owarimonogatari", "updated": "2023-02-14T12:30:45.689Z", "created": "2023-02-14T12:30:45.689Z"}}, {"model": "api.anime", "pk": 122, "fields": {"mal_id": 35247, "anime_title": "Owarimonogatari 2", "anime_score": "8.90", "airing_time": "Summer 2017", "studio": "SHAFT", "slug": "owarimonogatari-2", "updated": "2023-02-14T12:30:59.110Z", "created": "2023-02-14T12:30:59.110Z"}}, {"model": "api.anime", "pk": 123, "fields": {"mal_id": 28025, "anime_title": "Tsukimonogatari", "anime_score": "8.11", "airing_time": "Fall 2014", "studio": "SHAFT", "slug": "tsukimonogatari", "updated": "2023-02-14T12:31:13.845Z", "created": "2023-02-14T12:31:13.845Z"}}, {"model": "api.anime", "pk": 124, "fields": {"mal_id": 40708, "anime_title": "Monster Musume no Oisha-san", "anime_score": "6.25", "airing_time": "Summer 2020", "studio": "Arvo Animation", "slug": "monster-musume-no-oisha-san", "updated": "2023-02-14T12:31:34.146Z", "created": "2023-02-14T12:31:34.146Z"}}, {"model": "api.anime", "pk": 125, "fields": {"mal_id": 617, "anime_title": "Juubee Ninpuuchou", "anime_score": "7.61", "airing_time": "Spring 1993", "studio": "Madhouse", "slug": "juubee-ninpuuchou", "updated": "2023-02-14T12:31:52.739Z", "created": "2023-02-14T12:31:52.739Z"}}, {"model": "api.anime", "pk": 126, "fields": {"mal_id": 618, "anime_title": "Juubee Ninpuuchou - Ryuuhougyoku hen", "anime_score": "6.68", "airing_time": "Spring 2003", "studio": "Madhouse", "slug": "juubee-ninpuuchou-ryuuhougyoku-hen", "updated": "2023-02-14T12:32:10.517Z", "created": "2023-02-14T12:32:10.517Z"}}, {"model": "api.anime", "pk": 127, "fields": {"mal_id": 18897, "anime_title": "Nisekoi 1", "anime_score": "7.59", "airing_time": "Winter 2014", "studio": "SHAFT", "slug": "nisekoi-1", "updated": "2023-02-14T12:32:28.395Z", "created": "2023-02-14T12:32:28.395Z"}}, {"model": "api.anime", "pk": 128, "fields": {"mal_id": 27787, "anime_title": "Nisekoi 2", "anime_score": "7.36", "airing_time": "Spring 2015", "studio": "SHAFT", "slug": "nisekoi-2", "updated": "2023-02-14T12:32:46.027Z", "created": "2023-02-14T12:32:46.027Z"}}, {"model": "api.anime", "pk": 129, "fields": {"mal_id": 24227, "anime_title": "Nisekoi OVA", "anime_score": "7.37", "airing_time": "Fall 2014", "studio": "SHAFT", "slug": "nisekoi-ova", "updated": "2023-02-14T12:33:18.274Z", "created": "2023-02-14T12:33:18.274Z"}}, {"model": "api.anime", "pk": 130, "fields": {"mal_id": 41345, "anime_title": "Nobless", "anime_score": "6.87", "airing_time": "Fall 2020", "studio": "Production I.G", "slug": "nobless", "updated": "2023-02-14T12:33:30.501Z", "created": "2023-02-14T12:33:30.501Z"}}, {"model": "api.anime", "pk": 131, "fields": {"mal_id": 28819, "anime_title": "Okusama ga Seitokaichou", "anime_score": "6.60", "airing_time": "Summer 2015", "studio": "Seven", "slug": "okusama-ga-seitokaichou", "updated": "2023-02-14T12:33:42.659Z", "created": "2023-02-14T12:33:42.659Z"}}, {"model": "api.anime", "pk": 132, "fields": {"mal_id": 32603, "anime_title": "Okusama ga Seitokaichou +", "anime_score": "6.60", "airing_time": "Fall 2016", "studio": "Seven", "slug": "okusama-ga-seitokaichou", "updated": "2023-02-14T12:33:55.621Z", "created": "2023-02-14T12:33:55.621Z"}}, {"model": "api.anime", "pk": 133, "fields": {"mal_id": 41899, "anime_title": "Ore dake Haireru Kakushi Dungeon", "anime_score": "6.30", "airing_time": "Winter 2021", "studio": "Okuruto Noboru", "slug": "ore-dake-haireru-kakushi-dungeon", "updated": "2023-02-14T12:34:08.241Z", "created": "2023-02-14T12:34:08.241Z"}}, {"model": "api.anime", "pk": 134, "fields": {"mal_id": 29803, "anime_title": "Overlord I", "anime_score": "7.92", "airing_time": "Summer 2015", "studio": "Madhouse", "slug": "overlord-i", "updated": "2023-02-14T12:34:21.762Z", "created": "2023-02-14T12:34:21.762Z"}}, {"model": "api.anime", "pk": 135, "fields": {"mal_id": 35073, "anime_title": "Overlord II", "anime_score": "7.76", "airing_time": "Winter 2018", "studio": "Madhouse", "slug": "overlord-ii", "updated": "2023-02-14T12:34:51.258Z", "created": "2023-02-14T12:34:51.258Z"}}, {"model": "api.anime", "pk": 136, "fields": {"mal_id": 37675, "anime_title": "Overlord III", "anime_score": "7.92", "airing_time": "Summer 2018", "studio": "Madhouse", "slug": "overlord-iii", "updated": "2023-02-14T12:40:29.802Z", "created": "2023-02-14T12:40:29.802Z"}}, {"model": "api.anime", "pk": 137, "fields": {"mal_id": 48895, "anime_title": "Overlord IV", "anime_score": "8.33", "airing_time": "Summer 2022", "studio": "Madhouse", "slug": "overlord-iv", "updated": "2023-02-14T12:40:42.685Z", "created": "2023-02-14T12:40:42.685Z"}}, {"model": "api.anime", "pk": 138, "fields": {"mal_id": 30240, "anime_title": "Prison School", "anime_score": "7.62", "airing_time": "Summer 2015", "studio": "J.C.Staff", "slug": "prison-school", "updated": "2023-02-14T12:40:53.842Z", "created": "2023-02-14T12:40:53.842Z"}}, {"model": "api.anime", "pk": 139, "fields": {"mal_id": 2993, "anime_title": "Rosario to Vampire 1", "anime_score": "6.77", "airing_time": "Winter 2008", "studio": "Gonzo", "slug": "rosario-to-vampire-1", "updated": "2023-02-14T12:41:05.945Z", "created": "2023-02-14T12:41:05.945Z"}}, {"model": "api.anime", "pk": 140, "fields": {"mal_id": 4214, "anime_title": "Rosario to Vampire 2", "anime_score": "6.91", "airing_time": "Fall 2008", "studio": "Gonzo", "slug": "rosario-to-vampire-2", "updated": "2023-02-14T12:41:18.355Z", "created": "2023-02-14T12:41:18.355Z"}}, {"model": "api.berita", "pk": 1, "fields": {"content_title": "Inisialisasi Konten Pertama", "content_body": "Artikel ini merupakan inisialisasi data saat tabel database pertama kali dibuat. Kepada pengunjung dan member MyAnimeList Indonesia terhormat, jangan merasa terganggu dengan posting ini.", "writers": "author", "content_category": "dummy", "posted": "2023-02-15T08:43:04.178Z", "updated": "2023-02-15T08:43:24.470Z", "slug": "inisialisasi-konten-pertama"}}, {"model": "api.berita", "pk": 2, "fields": {"content_title": "Inisialisasi Konten Kedua", "content_body": "Berikut ini adalah inisialisasi konten yang kedua. Mohon untuk diabaikan saja jika muncul di beranda berita", "writers": "author", "content_category": "dummy", "posted": "2023-02-15T08:44:44.676Z", "updated": "2023-02-15T08:44:44.676Z", "slug": "inisialisasi-konten-kedua"}}, {"model": "api.berita", "pk": 3, "fields": {"content_title": "PENGUMUMAN MAINTENANCE", "content_body": "Karena aplikasi ini masih dalam tahap pengembangan, mohon kepada user untuk berhati-hati dalam memasukkan informasi pribadi. Apabila ada kerusakan atau hal-hal tidak wajar pada kinerja aplikasi ini, segera laporkan pada tim developer.", "writers": "author", "content_category": "announcement", "posted": "2023-02-15T09:11:03.450Z", "updated": "2023-02-15T09:11:03.450Z", "slug": "pengumuman-maintenance"}}, {"model": "api.berita", "pk": 4, "fields": {"content_title": "Serial BORUTO Dikabarkan Hiatus, Masashi Fokus Remake", "content_body": "Lorem ipsum dolor, sit amet consectetur adipisicing elit. Delectus magni molestiae praesentium deserunt perspiciatis, eius consequuntur quibusdam, illo possimus iusto exercitationem voluptates ducimus inventore ab? Beatae cum ea at facere. Lorem ipsum dolor, sit amet consectetur adipisicing elit. At aliquam velit consequuntur sunt maiores repellat ea, ducimus quos maxime voluptas ipsam rem corporis cupiditate, aspernatur eaque facere minima odit aperiam!", "writers": "author", "content_category": "hot_news", "posted": "2023-02-15T09:11:53.792Z", "updated": "2023-02-15T09:11:53.792Z", "slug": "serial-boruto-dikabarkan-hiatus-masashi-fokus-remake"}}, {"model": "api.berita", "pk": 5, "fields": {"content_title": "My Hero Academia Season 5 Siap Ditayangkan NET", "content_body": "My Hero Academia akan segera tayang lagi di NET. Hal ini terungkap melalui data dari Lembaga Sensor Film, di mana setidaknya sudah ada 3 episode season kelima yang telah lulus sensor. NET sendiri sebelumnya sempat dilaporkan telah memiliki anime ini hingga season kelima. Sebelumnya NET telah menayangkan season ketiga dan keempatnya. Di Jepang sendiri season keenamnya ditayangkan pada Oktober 2022. Pada season ketiga sebelumnya, NET mempercayakan Studio Shefai untuk mendubbing My Hero Academia. Adapun beberapa seiyu yang turut bermain di antaranya ada Irfan Setiawan,Tizar Sponsen, Salman Borneo, Uci Bismark, Kamal Nasuti, Ladi Carmelita, Barkah, Mohammad Romli, dll. Hal ini berbeda dengan RTV yang menggunakan Studio Erfas. Dikenal di Jepang dengan judul Boku no Hero Academia, anime My Hero Academia diangkat dari serial komik berjudul sama karya komikus asal Jepang Kohei Horikoshi. Serial komik ini pertama kali terbit di Jepang melalui majalah Weekly Shonen Jump pada Juli 2014 dan serial komiknya masih berjalan hingga kini. Karena kesuksesannya, komik ini akhirnya diadaptasi menjadi serial anime oleh Studio BONES yang telah tayang selama tiga musim. Serial anime yang juga dikenal di Jepang sebagai Boku no Hero Academia ini juga turut ditayangkan di Indonesia oleh RTV, dan saat ini tengah ditayangkan di NET. Adapun komiknya diterbitkan di Indonesia oleh penerbit m&c!. Komiknya sendiri juga akan diadaptasi menjadi proyek film Hollywood.", "writers": "author", "content_category": "hot_news", "posted": "2023-02-15T11:45:04.929Z", "updated": "2023-02-15T11:45:04.929Z", "slug": "my-hero-academia-season-5-siap-ditayangkan-net"}}]